reflectme
