Metadata-Version: 1.1
Name: reflectme
Version: 0.0.4
Summary: Simple HTTP server for recording requests and returning arbitrary responses.
Home-page: https://github.com/clavery/reflectme
Author: Charles Lavery
Author-email: charles.lavery@gmail.com
License: MIT License
Platform: UNKNOWN
Classifier: Development Status :: 3 - Alpha
Classifier: Intended Audience :: Developers
Classifier: Natural Language :: English
Classifier: License :: OSI Approved :: MIT License
Classifier: Programming Language :: Python
Classifier: Programming Language :: Python :: 2.6
Classifier: Programming Language :: Python :: 2.7
